dilated_attention_pytorch/__init__.py
dilated_attention_pytorch/dilated_attention.py
dilated_attention_pytorch/long_net.py
dilated_attention_pytorch/transformer.py
dilated_attention_pytorch-0.2.0.dist-info/LICENSE
dilated_attention_pytorch-0.2.0.dist-info/METADATA
dilated_attention_pytorch-0.2.0.dist-info/WHEEL
dilated_attention_pytorch-0.2.0.dist-info/top_level.txt
dilated_attention_pytorch-0.2.0.dist-info/RECORD
