Metadata-Version: 2.1
Name: dilated-attention-pytorch
Version: 0.2.0
Summary: project_description
Home-page: https://github.com/fkodom/dilated-attention-pytorch
Author: Frank Odom
Author-email: frank.odom.iii@gmail.com
Classifier: Programming Language :: Python :: 3
Classifier: Operating System :: OS Independent
Requires-Python: >=3.8
License-File: LICENSE
Requires-Dist: torch (>=1.8.0)
Requires-Dist: einops (~=0.6.0)
Requires-Dist: torchscale (~=0.2.0)
Requires-Dist: xformers (<0.0.22,>=0.0.20)
Provides-Extra: all
Requires-Dist: black ; extra == 'all'
Requires-Dist: flake8 ; extra == 'all'
Requires-Dist: isort ; extra == 'all'
Requires-Dist: kaleido ; extra == 'all'
Requires-Dist: mypy ; extra == 'all'
Requires-Dist: plotly ; extra == 'all'
Requires-Dist: pytest ; extra == 'all'
Requires-Dist: pytest-cov ; extra == 'all'
Requires-Dist: pre-commit ; extra == 'all'
Provides-Extra: dev
Requires-Dist: pre-commit ; extra == 'dev'
Requires-Dist: black ; extra == 'dev'
Requires-Dist: flake8 ; extra == 'dev'
Requires-Dist: isort ; extra == 'dev'
Requires-Dist: kaleido ; extra == 'dev'
Requires-Dist: mypy ; extra == 'dev'
Requires-Dist: plotly ; extra == 'dev'
Requires-Dist: pytest ; extra == 'dev'
Requires-Dist: pytest-cov ; extra == 'dev'
Provides-Extra: test
Requires-Dist: black ; extra == 'test'
Requires-Dist: flake8 ; extra == 'test'
Requires-Dist: isort ; extra == 'test'
Requires-Dist: kaleido ; extra == 'test'
Requires-Dist: mypy ; extra == 'test'
Requires-Dist: plotly ; extra == 'test'
Requires-Dist: pytest ; extra == 'test'
Requires-Dist: pytest-cov ; extra == 'test'
